tabsdata_databricks-1.5.0.data/purelib/tabsdata_databricks/__init__.py
tabsdata_databricks-1.5.0.data/purelib/tabsdata_databricks/_connector.py
tabsdata_databricks-1.5.0.data/purelib/tabsdata_databricks/assets/manifest/BANNER
tabsdata_databricks-1.5.0.data/purelib/tabsdata_databricks/assets/manifest/LICENSE
tabsdata_databricks-1.5.0.data/purelib/tabsdata_databricks/assets/manifest/README-PyPi.md
tabsdata_databricks-1.5.0.data/purelib/tabsdata_databricks/assets/manifest/RELEASE-NOTES
tabsdata_databricks-1.5.0.data/purelib/tabsdata_databricks/assets/manifest/SOURCETRACK.yaml
tabsdata_databricks-1.5.0.data/purelib/tabsdata_databricks/assets/manifest/THIRD-PARTY
tabsdata_databricks-1.5.0.data/purelib/tabsdata_databricks/assets/manifest/VERSION
tabsdata_databricks-1.5.0.dist-info/licenses/tabsdata_databricks/assets/manifest/LICENSE
tabsdata_databricks-1.5.0.dist-info/METADATA
tabsdata_databricks-1.5.0.dist-info/WHEEL
tabsdata_databricks-1.5.0.dist-info/top_level.txt
tabsdata_databricks-1.5.0.dist-info/RECORD
